.VERSION
AUTHORS.rst
CONTRIBUTING.rst
HISTORY.rst
LICENSE
MANIFEST.in
Pipfile
Pipfile.lock
README.rst
USAGE.rst
dev-requirements.txt
requirements.txt
setup.cfg
setup.py
docs/Makefile
docs/authors.rst
docs/conf.py
docs/contributing.rst
docs/history.rst
docs/index.rst
docs/installation.rst
docs/readme.rst
docs/usage.rst
tests/test_wikiseriessjoerdtoolcli.py
wikiseriessjoerdtoolcli/.VERSION
wikiseriessjoerdtoolcli/AUTHORS.rst
wikiseriessjoerdtoolcli/CONTRIBUTING.rst
wikiseriessjoerdtoolcli/HISTORY.rst
wikiseriessjoerdtoolcli/LICENSE
wikiseriessjoerdtoolcli/Pipfile
wikiseriessjoerdtoolcli/Pipfile.lock
wikiseriessjoerdtoolcli/README.rst
wikiseriessjoerdtoolcli/USAGE.rst
wikiseriessjoerdtoolcli/__init__.py
wikiseriessjoerdtoolcli/_version.py
wikiseriessjoerdtoolcli/dev-requirements.txt
wikiseriessjoerdtoolcli/requirements.txt
wikiseriessjoerdtoolcli/wikiseriessjoerdtoolcli.py
wikiseriessjoerdtoolcli/wikiseriessjoerdtoolcliexceptions.py
wikiseriessjoerdtoolcli.egg-info/PKG-INFO
wikiseriessjoerdtoolcli.egg-info/SOURCES.txt
wikiseriessjoerdtoolcli.egg-info/dependency_links.txt
wikiseriessjoerdtoolcli.egg-info/entry_points.txt
wikiseriessjoerdtoolcli.egg-info/not-zip-safe
wikiseriessjoerdtoolcli.egg-info/requires.txt
wikiseriessjoerdtoolcli.egg-info/top_level.txt
wikiseriessjoerdtoolcli/conf/logging.json-example