Metadata-Version: 2.1
Name: wikiseriessjoerdtoolcli
Version: 0.1.1
Summary: A cli tool to use wikipedia to retrieve tv series information
Home-page: https://github.com/sjoerdvdbos/wikiseriessjoerdtoolcli
Author: Sjoerd van den Bos
Author-email: test@example.com
License: MIT
Keywords: wikiseriessjoerdtoolcli
Classifier: Development Status :: 3 - Alpha
Classifier: Intended Audience :: Developers
Classifier: License :: OSI Approved :: MIT License
Classifier: Natural Language :: English
Classifier: Programming Language :: Python :: 3.9
License-File: LICENSE
License-File: AUTHORS.rst
